{
  "companies": [
    {"id": 1, "compName": "comapany_1", "city": "city_1", "address": "address_1"},
    {"id": 2, "compName": "comapany_2", "city": "city_2"," address": "address_2"},
    {"id": 3, "compName": "comapany_3", "city": "city_3", "address": "address_3"},
    {"id": 4, "compName": "comapany_4", "city": "city_4", "address": "address_4"},
    {"id": 5, "compName": "comapany_5", "city": "city_5", "address": "address_5"},
    {"id": 6, "compName": "comapany_6", "city": "city_6", "address": "address_6"},
    {"id": 7, "compName": "comapany_7", "city": "city_7", "address": "address_7"},
    {"id": 8, "compName": "comapany_8", "city": "city_8", "address": "address_8"},
    {"id": 9, "compName": "comapany_9", "city": "city_9", "address": "address_9"},
    {"id": 10, "compName": "comapany_10", "city": "city_10", "address": "address_10"}
  ],
  "contacts": [
    {"id": 1, "compId": 1, "name": "name_1", "telephone": "telephone_1"},
    {"id": 2, "compId": 1, "name": "name_2", "telephone": "telephone_2"},
    {"id": 3, "compId": 1, "name": "name_3", "telephone": "telephone_3"},
    {"id": 4, "compId": 1, "name": "name_4", "telephone": "telephone_4"},
    {"id": 5, "compId": 2, "name": "name_5", "telephone": "telephone_5"},
    {"id": 6, "compId": 3, "name": "name_6", "telephone": "telephone_6"},
    {"id": 7, "compId": 4, "name": "name_7", "telephone": "telephone_7"},
    {"id": 8, "compId": 5, "name": "name_8", "telephone": "telephone_8"},
    {"id": 9, "compId": 6, "name": "name_9", "telephone": "telephone_9"},
    {"id": 10, "compId": 6, "name": "name_10", "telephone": "telephone_10"},
    {"id": 11, "compId": 7, "name": "name_11", "telephone": "telephone_11"},
    {"id": 12, "compId": 8, "name": "name_12", "telephone": "telephone_12"},
    {"id": 13, "compId": 1, "name": "name_13", "telephone": "telephone_13"},
    {"id": 14, "compId": 2, "name": "name_14", "telephone": "telephone_14"},
    {"id": 15, "compId": 3, "name": "name_15", "telephone": "telephone_15"},
    {"id": 16, "compId": 1, "name": "name_16", "telephone": "telephone_16"},
    {"id": 17, "compId": 2, "name": "name_17", "telephone": "telephone_17"},
    {"id": 18, "compId": 3, "name": "name_18", "telephone": "telephone_18"}
  ]
}